LICENSE
README.rst
setup.cfg
setup.py
cfn_resource_provider/__init__.py
cfn_resource_provider/default_injecting_validator.py
cfn_resource_provider/resource_provider.py
cfn_resource_provider/sns_envelope.py
cfn_resource_provider.egg-info/PKG-INFO
cfn_resource_provider.egg-info/SOURCES.txt
cfn_resource_provider.egg-info/dependency_links.txt
cfn_resource_provider.egg-info/not-zip-safe
cfn_resource_provider.egg-info/requires.txt
cfn_resource_provider.egg-info/top_level.txt
tests/test_cfn_provider.py
tests/test_sns_envelope.py