Metadata-Version: 2.1
Name: cfn-resource-provider
Version: 1.2.1
Summary: A base class for AWS CloudFormation Custom Resource Providers.
Home-page: https://github.com/binxio/cfn-resource-provider
Author: Mark van Holsteijn
Author-email: markvanholsteijn@binx.io
Platform: any
License-File: LICENSE
